ocroy/__init__.py
ocroy/__main__.py
ocroy/normalize.py
ocroy/parser.py
ocroy/reader.py
ocroy/recognizers/__init__.py
ocroy/recognizers/base.py
ocroy/recognizers/core.py
ocroy/recognizers/google_vision_api.py
ocroy/recognizers/tesseract.py
ocroy-0.1.2.dist-info/LICENSE
ocroy-0.1.2.dist-info/METADATA
ocroy-0.1.2.dist-info/WHEEL
ocroy-0.1.2.dist-info/entry_points.txt
ocroy-0.1.2.dist-info/top_level.txt
ocroy-0.1.2.dist-info/RECORD
